IntDivisor32bits/Behavioral/divisor.v

module test();

    reg [31:0] div,den;
    reg clk;
    wire [31:0] q,r;


    divisor32b divsr(div,den,clk,q,r);

    always
        #5 clk = ~clk;

    initial begin
        clk = 0;
        den =2**31;
        div = 12354;
        $monitor("%d%d = %d %d",den,div,q,r);
        #900 $finish;
    end

    initial begin
        $dumpfile("div.vcd");
        $dumpvars(0,test);
    end

endmodule




module divisor32b(input[31:0] divisor, dividend, input clk, output reg [31:0] quotient, remainder);

    reg [5:0] count;
    wire [32:0] sub;
    reg [32:0] remainderTemp;
    reg [31:0] quotientTemp;
    reg [31:0] divisorTemp;
    assign sub = {1'b0,remainderTemp} - {1'b0,divisorTemp};

    initial
        count  = 0;

    always@(posedge clk) begin
        //incrementa el contador
        
        if(count==0) begin 
            remainderTemp=33'd0;
            quotientTemp = dividend;
            divisorTemp = divisor;
        end


        count = count +1;
       
        //si la resta da positivo entonces se asigna
        if(~sub[32]) remainderTemp[31:0] = sub[31:0];
        remainderTemp = remainderTemp<<1 | {31'b0,quotientTemp[31]};
        quotientTemp = quotientTemp <<1 | {31'b0,~sub[32]};

        if(count==33) begin
            count = 0;
            quotient = quotientTemp;
            remainder = remainderTemp[32:1];
        end
        

    end
endmodule

IntDivisor32bits/Behavioral/div.vcd
$date
	Tue Sep 27 23:28:21 2022
$end
$version
	Icarus Verilog
$end
$timescale
	1s
$end
$scope module test $end
$var wire 32 ! r [31:0] $end
$var wire 32 " q [31:0] $end
$var reg 1 # clk $end
$var reg 32 $ den [31:0] $end
$var reg 32 % div [31:0] $end
$scope module divsr $end
$var wire 1 # clk $end
$var wire 32 & dividend [31:0] $end
$var wire 32 ' divisor [31:0] $end
$var wire 33 ( sub [32:0] $end
$var reg 6 ) count [5:0] $end
$var reg 32 * divisorTemp [31:0] $end
$var reg 32 + quotient [31:0] $end
$var reg 32 , quotientTemp [31:0] $end
$var reg 32 - remainder [31:0] $end
$var reg 33 . remainderTemp [32:0] $end
$upscope $end
$upscope $end
$enddefinitions $end
$comment Show the parameter values. $end
$dumpall
$end
#0
$dumpvars
bx .
bx -
bx ,
bx +
bx *
b0 )
bx (
b11000001000010 '
b10000000000000000000000000000000 &
b11000001000010 %
b10000000000000000000000000000000 $
0#
bx "
bx !
$end
#5
b111111111111111111100111110111111 (
b1 )
b11000001000010 *
b0x ,
b1 .
1#
#10
0#
#15
b111111111111111111100111111000000 (
b0x0 ,
b10 .
b10 )
1#
#20
0#
#25
b111111111111111111100111111000010 (
b0x00 ,
b100 .
b11 )
1#
#30
0#
#35
b111111111111111111100111111000110 (
b0x000 ,
b1000 .
b100 )
1#
#40
0#
#45
b111111111111111111100111111001110 (
b0x0000 ,
b10000 .
b101 )
1#
#50
0#
#55
b111111111111111111100111111011110 (
b0x00000 ,
b100000 .
b110 )
1#
#60
0#
#65
b111111111111111111100111111111110 (
b0x000000 ,
b1000000 .
b111 )
1#
#70
0#
#75
b111111111111111111101000000111110 (
b0x0000000 ,
b10000000 .
b1000 )
1#
#80
0#
#85
b111111111111111111101000010111110 (
b0x00000000 ,
b100000000 .
b1001 )
1#
#90
0#
#95
b111111111111111111101000110111110 (
b0x000000000 ,
b1000000000 .
b1010 )
1#
#100
0#
#105
b111111111111111111101001110111110 (
b0x0000000000 ,
b10000000000 .
b1011 )
1#
#110
0#
#115
b111111111111111111101011110111110 (
b0x00000000000 ,
b100000000000 .
b1100 )
1#
#120
0#
#125
b111111111111111111101111110111110 (
b0x000000000000 ,
b1000000000000 .
b1101 )
1#
#130
0#
#135
b111111111111111111110111110111110 (
b0x0000000000000 ,
b10000000000000 .
b1110 )
1#
#140
0#
#145
b111110111110 (
b0x00000000000000 ,
b100000000000000 .
b1111 )
1#
#150
0#
#155
b111111111111111111110111100111010 (
b0x000000000000001 ,
b1111101111100 .
b10000 )
1#
#160
0#
#165
b111010110110 (
b0x0000000000000010 ,
b11111011111000 .
b10001 )
1#
#170
0#
#175
b111111111111111111110110100101010 (
b0x00000000000000101 ,
b1110101101100 .
b10010 )
1#
#180
0#
#185
b101010010110 (
b0x000000000000001010 ,
b11101011011000 .
b10011 )
1#
#190
0#
#195
b111111111111111111110010011101010 (
b0x0000000000000010101 ,
b1010100101100 .
b10100 )
1#
#200
0#
#205
b111111111111111111111101000010110 (
b0x00000000000000101010 ,
b10101001011000 .
b10101 )
1#
#210
0#
#215
b10010001101110 (
b0x000000000000001010100 ,
b101010010110000 .
b10110 )
1#
#220
0#
#225
b1100010011010 (
b0x0000000000000010101001 ,
b100100011011100 .
b10111 )
1#
#230
0#
#235
b11110010 (
b0x00000000000000101010011 ,
b11000100110100 .
b11000 )
1#
#240
0#
#245
b111111111111111111101000110100010 (
b0x000000000000001010100111 ,
b111100100 .
b11001 )
1#
#250
0#
#255
b111111111111111111101001110000110 (
b0x0000000000000010101001110 ,
b1111001000 .
b11010 )
1#
#260
0#
#265
b111111111111111111101011101001110 (
b0x00000000000000101010011100 ,
b11110010000 .
b11011 )
1#
#270
0#
#275
b111111111111111111101111011011110 (
b0x000000000000001010100111000 ,
b111100100000 .
b11100 )
1#
#280
0#
#285
b111111111111111111110110111111110 (
b0x0000000000000010101001110000 ,
b1111001000000 .
b11101 )
1#
#290
0#
#295
b110000111110 (
b0x00000000000000101010011100000 ,
b11110010000000 .
b11110 )
1#
#300
0#
#305
b111111111111111111110100000111010 (
b0x000000000000001010100111000001 ,
b1100001111100 .
b11111 )
1#
#310
0#
#315
b10110110 (
bx0000000000000010101001110000010 ,
b11000011111000 .
b100000 )
1#
#320
0#
#325
bx (
b10110110 !
b10110110 -
b101010011100000101 "
b101010011100000101 +
b101010011100000101 ,
b10110110x .
b0 )
1#
#330
0#
#335
b111111111111111111100111110111111 (
b1 )
b0x ,
b1 .
1#
#340
0#
#345
b111111111111111111100111111000000 (
b0x0 ,
b10 .
b10 )
1#
#350
0#
#355
b111111111111111111100111111000010 (
b0x00 ,
b100 .
b11 )
1#
#360
0#
#365
b111111111111111111100111111000110 (
b0x000 ,
b1000 .
b100 )
1#
#370
0#
#375
b111111111111111111100111111001110 (
b0x0000 ,
b10000 .
b101 )
1#
#380
0#
#385
b111111111111111111100111111011110 (
b0x00000 ,
b100000 .
b110 )
1#
#390
0#
#395
b111111111111111111100111111111110 (
b0x000000 ,
b1000000 .
b111 )
1#
#400
0#
#405
b111111111111111111101000000111110 (
b0x0000000 ,
b10000000 .
b1000 )
1#
#410
0#
#415
b111111111111111111101000010111110 (
b0x00000000 ,
b100000000 .
b1001 )
1#
#420
0#
#425
b111111111111111111101000110111110 (
b0x000000000 ,
b1000000000 .
b1010 )
1#
#430
0#
#435
b111111111111111111101001110111110 (
b0x0000000000 ,
b10000000000 .
b1011 )
1#
#440
0#
#445
b111111111111111111101011110111110 (
b0x00000000000 ,
b100000000000 .
b1100 )
1#
#450
0#
#455
b111111111111111111101111110111110 (
b0x000000000000 ,
b1000000000000 .
b1101 )
1#
#460
0#
#465
b111111111111111111110111110111110 (
b0x0000000000000 ,
b10000000000000 .
b1110 )
1#
#470
0#
#475
b111110111110 (
b0x00000000000000 ,
b100000000000000 .
b1111 )
1#
#480
0#
#485
b111111111111111111110111100111010 (
b0x000000000000001 ,
b1111101111100 .
b10000 )
1#
#490
0#
#495
b111010110110 (
b0x0000000000000010 ,
b11111011111000 .
b10001 )
1#
#500
0#
#505
b111111111111111111110110100101010 (
b0x00000000000000101 ,
b1110101101100 .
b10010 )
1#
#510
0#
#515
b101010010110 (
b0x000000000000001010 ,
b11101011011000 .
b10011 )
1#
#520
0#
#525
b111111111111111111110010011101010 (
b0x0000000000000010101 ,
b1010100101100 .
b10100 )
1#
#530
0#
#535
b111111111111111111111101000010110 (
b0x00000000000000101010 ,
b10101001011000 .
b10101 )
1#
#540
0#
#545
b10010001101110 (
b0x000000000000001010100 ,
b101010010110000 .
b10110 )
1#
#550
0#
#555
b1100010011010 (
b0x0000000000000010101001 ,
b100100011011100 .
b10111 )
1#
#560
0#
#565
b11110010 (
b0x00000000000000101010011 ,
b11000100110100 .
b11000 )
1#
#570
0#
#575
b111111111111111111101000110100010 (
b0x000000000000001010100111 ,
b111100100 .
b11001 )
1#
#580
0#
#585
b111111111111111111101001110000110 (
b0x0000000000000010101001110 ,
b1111001000 .
b11010 )
1#
#590
0#
#595
b111111111111111111101011101001110 (
b0x00000000000000101010011100 ,
b11110010000 .
b11011 )
1#
#600
0#
#605
b111111111111111111101111011011110 (
b0x000000000000001010100111000 ,
b111100100000 .
b11100 )
1#
#610
0#
#615
b111111111111111111110110111111110 (
b0x0000000000000010101001110000 ,
b1111001000000 .
b11101 )
1#
#620
0#
#625
b110000111110 (
b0x00000000000000101010011100000 ,
b11110010000000 .
b11110 )
1#
#630
0#
#635
b111111111111111111110100000111010 (
b0x000000000000001010100111000001 ,
b1100001111100 .
b11111 )
1#
#640
0#
#645
b10110110 (
bx0000000000000010101001110000010 ,
b11000011111000 .
b100000 )
1#
#650
0#
#655
bx (
b101010011100000101 ,
b10110110x .
b0 )
1#
#660
0#
#665
b111111111111111111100111110111111 (
b1 )
b0x ,
b1 .
1#
#670
0#
#675
b111111111111111111100111111000000 (
b0x0 ,
b10 .
b10 )
1#
#680
0#
#685
b111111111111111111100111111000010 (
b0x00 ,
b100 .
b11 )
1#
#690
0#
#695
b111111111111111111100111111000110 (
b0x000 ,
b1000 .
b100 )
1#
#700
0#
#705
b111111111111111111100111111001110 (
b0x0000 ,
b10000 .
b101 )
1#
#710
0#
#715
b111111111111111111100111111011110 (
b0x00000 ,
b100000 .
b110 )
1#
#720
0#
#725
b111111111111111111100111111111110 (
b0x000000 ,
b1000000 .
b111 )
1#
#730
0#
#735
b111111111111111111101000000111110 (
b0x0000000 ,
b10000000 .
b1000 )
1#
#740
0#
#745
b111111111111111111101000010111110 (
b0x00000000 ,
b100000000 .
b1001 )
1#
#750
0#
#755
b111111111111111111101000110111110 (
b0x000000000 ,
b1000000000 .
b1010 )
1#
#760
0#
#765
b111111111111111111101001110111110 (
b0x0000000000 ,
b10000000000 .
b1011 )
1#
#770
0#
#775
b111111111111111111101011110111110 (
b0x00000000000 ,
b100000000000 .
b1100 )
1#
#780
0#
#785
b111111111111111111101111110111110 (
b0x000000000000 ,
b1000000000000 .
b1101 )
1#
#790
0#
#795
b111111111111111111110111110111110 (
b0x0000000000000 ,
b10000000000000 .
b1110 )
1#
#800
0#
#805
b111110111110 (
b0x00000000000000 ,
b100000000000000 .
b1111 )
1#
#810
0#
#815
b111111111111111111110111100111010 (
b0x000000000000001 ,
b1111101111100 .
b10000 )
1#
#820
0#
#825
b111010110110 (
b0x0000000000000010 ,
b11111011111000 .
b10001 )
1#
#830
0#
#835
b111111111111111111110110100101010 (
b0x00000000000000101 ,
b1110101101100 .
b10010 )
1#
#840
0#
#845
b101010010110 (
b0x000000000000001010 ,
b11101011011000 .
b10011 )
1#
#850
0#
#855
b111111111111111111110010011101010 (
b0x0000000000000010101 ,
b1010100101100 .
b10100 )
1#
#860
0#
#865
b111111111111111111111101000010110 (
b0x00000000000000101010 ,
b10101001011000 .
b10101 )
1#
#870
0#
#875
b10010001101110 (
b0x000000000000001010100 ,
b101010010110000 .
b10110 )
1#
#880
0#
#885
b1100010011010 (
b0x0000000000000010101001 ,
b100100011011100 .
b10111 )
1#
#890
0#
#895
b11110010 (
b0x00000000000000101010011 ,
b11000100110100 .
b11000 )
1#
